superset_chat/ai_superset_assistant.py
superset_chat/app/__init__.py
superset_chat/app/databases/__init__.py
superset_chat/app/databases/postgres.py
superset_chat/app/models/__init__.py
superset_chat/app/models/inference/__init__.py
superset_chat/app/models/inference/antropic_model.py
superset_chat/app/models/inference/bedrock_model.py
superset_chat/app/models/inference/openai_model.py
superset_chat/app/server/__init__.py
superset_chat/app/server/llm.py
superset_chat/app/utils/__init__.py
superset_chat/app/utils/config.py
superset_chat/app/utils/logger.py
superset_chat/app/utils/singleton.py
superset_chat/templates/ai_assistant.html
superset_chat-0.1.0a24.dist-info/METADATA
superset_chat-0.1.0a24.dist-info/WHEEL
superset_chat-0.1.0a24.dist-info/licenses/LICENSE
superset_chat-0.1.0a24.dist-info/RECORD
