Metadata-Version: 2.4
Name: superset-chat
Version: 0.1.0a24
Summary: AI Assistant plugin for Apache Superset
License: MIT
License-File: LICENSE
Author: Ponder
Requires-Python: >=3.10,<4.0
Classifier: License :: OSI Approved :: MIT License
Classifier: Programming Language :: Python :: 3
Classifier: Programming Language :: Python :: 3.10
Classifier: Programming Language :: Python :: 3.11
Classifier: Programming Language :: Python :: 3.12
Classifier: Programming Language :: Python :: 3.13
Classifier: Programming Language :: Python :: 3.14
Requires-Dist: PyJWT (==2.8.0)
Requires-Dist: SQLAlchemy (>=1.4.0)
Requires-Dist: dbt-graph-loader (==0.1.0a1)
Requires-Dist: flask (>=2.0.0)
Requires-Dist: flask-appbuilder (>=3.0.0)
Requires-Dist: httpx
Requires-Dist: langchain (>=0.3,<0.4)
Requires-Dist: langchain-anthropic (==0.3)
Requires-Dist: langchain-aws (==0.2)
Requires-Dist: langchain-community (==0.3)
Requires-Dist: langchain-core
Requires-Dist: langchain-mcp-adapters
Requires-Dist: langchain-neo4j (>=0.4.0,<0.5.0)
Requires-Dist: langchain-openai (==0.3)
Requires-Dist: langchain-text-splitters (==0.3)
Requires-Dist: langfuse
Requires-Dist: langgraph (==0.5)
Requires-Dist: langgraph-checkpoint-postgres (==2.0)
Requires-Dist: langgraph-checkpoint-sqlite (==2.0)
Requires-Dist: mcp
Requires-Dist: psycopg (==3.2)
Requires-Dist: superset-mcp-server (==0.1.0a5)
Project-URL: homepage, https://github.com/ponderedw/superset-mcp-plugins
